{
	"_type": "export",
	"__export_format": 3,
	"__export_date": "2023-10-31T00:51:24.537Z",
	"__export_source": "insomnia.desktop.app:v6.2.0",
	"resources": [
		{
			"_id": "wrk_967dea47922b4578ae31ce5d938e7db8",
			"created": 1698673166286,
			"description": "",
			"modified": 1698673166286,
			"name": "Insomnia",
			"parentId": null,
			"_type": "workspace"
		},
		{
			"_id": "env_9dd2ab5c873049b58b4b1273e1da9b34",
			"color": null,
			"created": 1698673166331,
			"data": {},
			"isPrivate": false,
			"metaSortKey": 1698673166331,
			"modified": 1698673166331,
			"name": "New Environment",
			"parentId": "wrk_967dea47922b4578ae31ce5d938e7db8",
			"_type": "environment"
		},
		{
			"_id": "jar_97347d92f08d422cbc6a1d6bcb7243b3",
			"cookies": [],
			"created": 1698673166333,
			"modified": 1698673166333,
			"name": "Default Jar",
			"parentId": "wrk_967dea47922b4578ae31ce5d938e7db8",
			"_type": "cookie_jar"
		},
		{
			"_id": "fld_a13402fa5996453ba52c48b74f8d2c4f",
			"created": 1698673291274,
			"description": "",
			"environment": {},
			"metaSortKey": -1698673291274,
			"modified": 1698673291274,
			"name": "blockchain_api",
			"parentId": "wrk_967dea47922b4578ae31ce5d938e7db8",
			"_type": "request_group"
		},
		{
			"_id": "req_81f406b3a6ce42ba891c3a8b72d71c72",
			"authentication": {},
			"body": {
				"mimeType": "application/json",
				"text": ""
			},
			"created": 1698673731378,
			"description": "",
			"headers": [
				{
					"id": "pair_8386e35d0f96459e956ada9908f36a33",
					"name": "",
					"value": ""
				},
				{
					"id": "pair_1043521ad6c84617b4ad8221af499499",
					"name": "Content-Type",
					"value": "application/json"
				}
			],
			"isPrivate": false,
			"metaSortKey": -1698673731378,
			"method": "GET",
			"modified": 1698700128289,
			"name": "hi",
			"parameters": [],
			"parentId": "fld_a13402fa5996453ba52c48b74f8d2c4f",
			"settingDisableRenderRequestBody": false,
			"settingEncodeUrl": true,
			"settingMaxTimelineDataSize": 1000,
			"settingRebuildPath": true,
			"settingSendCookies": true,
			"settingStoreCookies": true,
			"url": "http://127.0.0.1:5000/",
			"_type": "request"
		},
		{
			"_id": "req_1dd0583a61c844a3b9a1e699e4b53f61",
			"authentication": {},
			"body": {
				"mimeType": "application/json",
				"text": "{\n\t\"sender\": \"19sXoSbfcQD9K66f5hwP5vLwsaRyKLPgXF\",\n\t\"recipient\": \"1MxTkeEP2PmHSMze5tUZ1hAV3YTKu2Gh1N\",\n\t\"amount\": 0.5,\n\t\"timestamp\": 0,\n\t\"privWifKey\": \"L1US57sChKZeyXrev9q7tFm2dgA2ktJe2NP3xzXRv6wizom5MN1U\"\n}"
			},
			"created": 1698687457913,
			"description": "",
			"headers": [
				{
					"id": "pair_6c06e970ddf64ca8be560eac1589b12f",
					"name": "Content-Type",
					"value": "application/json"
				}
			],
			"isPrivate": false,
			"metaSortKey": -1698701682954,
			"method": "POST",
			"modified": 1698713213658,
			"name": "transactions_create",
			"parameters": [],
			"parentId": "fld_a13402fa5996453ba52c48b74f8d2c4f",
			"settingDisableRenderRequestBody": false,
			"settingEncodeUrl": true,
			"settingMaxTimelineDataSize": 1000,
			"settingRebuildPath": true,
			"settingSendCookies": true,
			"settingStoreCookies": true,
			"url": "http://127.0.0.1:5001/transactions/create",
			"_type": "request"
		},
		{
			"_id": "req_6a5712c0150f41aa941b65489b393859",
			"authentication": {},
			"body": {},
			"created": 1698688328168,
			"description": "",
			"headers": [],
			"isPrivate": false,
			"metaSortKey": -1698701682904,
			"method": "GET",
			"modified": 1698713222636,
			"name": "transactions_mempool",
			"parameters": [],
			"parentId": "fld_a13402fa5996453ba52c48b74f8d2c4f",
			"settingDisableRenderRequestBody": false,
			"settingEncodeUrl": true,
			"settingMaxTimelineDataSize": 1000,
			"settingRebuildPath": true,
			"settingSendCookies": true,
			"settingStoreCookies": true,
			"url": "http://127.0.0.1:5001//transactions/mempool",
			"_type": "request"
		},
		{
			"_id": "req_ccacfe6cd3a345bc91f2519ea745b09a",
			"authentication": {},
			"body": {},
			"created": 1698699793196,
			"description": "",
			"headers": [],
			"isPrivate": false,
			"metaSortKey": -1698701682866.5,
			"method": "GET",
			"modified": 1698713251078,
			"name": "chain",
			"parameters": [],
			"parentId": "fld_a13402fa5996453ba52c48b74f8d2c4f",
			"settingDisableRenderRequestBody": false,
			"settingEncodeUrl": true,
			"settingMaxTimelineDataSize": 1000,
			"settingRebuildPath": true,
			"settingSendCookies": true,
			"settingStoreCookies": true,
			"url": "http://127.0.0.1:5001/chain",
			"_type": "request"
		},
		{
			"_id": "req_f0c5aedfb121444683bec7a598149b2b",
			"authentication": {},
			"body": {},
			"created": 1698699836973,
			"description": "",
			"headers": [],
			"isPrivate": false,
			"metaSortKey": -1698701682879,
			"method": "GET",
			"modified": 1698713234247,
			"name": "mine",
			"parameters": [],
			"parentId": "fld_a13402fa5996453ba52c48b74f8d2c4f",
			"settingDisableRenderRequestBody": false,
			"settingEncodeUrl": true,
			"settingMaxTimelineDataSize": 1000,
			"settingRebuildPath": true,
			"settingSendCookies": true,
			"settingStoreCookies": true,
			"url": "http://127.0.0.1:5001/mine",
			"_type": "request"
		},
		{
			"_id": "req_fd8a4a1da08240b5b42014c459e68d0c",
			"authentication": {},
			"body": {
				"mimeType": "application/json",
				"text": "{\n\t\"url\": \"http://127.0.0.1:5002/\"\n}"
			},
			"created": 1698699973387,
			"description": "",
			"headers": [
				{
					"id": "pair_fd3ee4061d644bb085d46fba5e849161",
					"name": "Content-Type",
					"value": "application/json"
				}
			],
			"isPrivate": false,
			"metaSortKey": -1698701682860.25,
			"method": "POST",
			"modified": 1698713257394,
			"name": "register",
			"parameters": [],
			"parentId": "fld_a13402fa5996453ba52c48b74f8d2c4f",
			"settingDisableRenderRequestBody": false,
			"settingEncodeUrl": true,
			"settingMaxTimelineDataSize": 1000,
			"settingRebuildPath": true,
			"settingSendCookies": true,
			"settingStoreCookies": true,
			"url": "http://127.0.0.1:5001/nodes/register",
			"_type": "request"
		},
		{
			"_id": "req_5818e2c786014bd58b0e1fa5b3b30308",
			"authentication": {},
			"body": {},
			"created": 1698700656053,
			"description": "",
			"headers": [],
			"isPrivate": false,
			"metaSortKey": -1698701682857.125,
			"method": "GET",
			"modified": 1698713262378,
			"name": "resolve",
			"parameters": [],
			"parentId": "fld_a13402fa5996453ba52c48b74f8d2c4f",
			"settingDisableRenderRequestBody": false,
			"settingEncodeUrl": true,
			"settingMaxTimelineDataSize": 1000,
			"settingRebuildPath": true,
			"settingSendCookies": true,
			"settingStoreCookies": true,
			"url": "http://127.0.0.1:5001/nodes/resolve",
			"_type": "request"
		},
		{
			"_id": "req_23d6d165633b40919a9559382ade474e",
			"authentication": {},
			"body": {},
			"created": 1698701504070,
			"description": "",
			"headers": [],
			"isPrivate": false,
			"metaSortKey": -1698701682855.5625,
			"method": "GET",
			"modified": 1698713278928,
			"name": "mine2",
			"parameters": [],
			"parentId": "fld_a13402fa5996453ba52c48b74f8d2c4f",
			"settingDisableRenderRequestBody": false,
			"settingEncodeUrl": true,
			"settingMaxTimelineDataSize": 1000,
			"settingRebuildPath": true,
			"settingSendCookies": true,
			"settingStoreCookies": true,
			"url": "http://127.0.0.1:5002/mine",
			"_type": "request"
		},
		{
			"_id": "req_e437ab45a8d54cd2bf64f33b0d95e9e7",
			"authentication": {},
			"body": {},
			"created": 1698701569775,
			"description": "",
			"headers": [],
			"isPrivate": false,
			"metaSortKey": -1698701682854.7812,
			"method": "GET",
			"modified": 1698713313353,
			"name": "chain2",
			"parameters": [],
			"parentId": "fld_a13402fa5996453ba52c48b74f8d2c4f",
			"settingDisableRenderRequestBody": false,
			"settingEncodeUrl": true,
			"settingMaxTimelineDataSize": 1000,
			"settingRebuildPath": true,
			"settingSendCookies": true,
			"settingStoreCookies": true,
			"url": "http://127.0.0.1:5002/chain",
			"_type": "request"
		},
		{
			"_id": "req_5aa2aace6bf0427f99f2af9505e3f171",
			"authentication": {},
			"body": {
				"mimeType": "application/json",
				"text": "{\n\t\"url\": \"http://127.0.0.1:5001/\"\n}"
			},
			"created": 1698701596711,
			"description": "",
			"headers": [
				{
					"id": "pair_b089304af6ec477ca12954f8a45958ab",
					"name": "Content-Type",
					"value": "application/json"
				}
			],
			"isPrivate": false,
			"metaSortKey": -1698701670942.3906,
			"method": "POST",
			"modified": 1698713290057,
			"name": "register2",
			"parameters": [],
			"parentId": "fld_a13402fa5996453ba52c48b74f8d2c4f",
			"settingDisableRenderRequestBody": false,
			"settingEncodeUrl": true,
			"settingMaxTimelineDataSize": 1000,
			"settingRebuildPath": true,
			"settingSendCookies": true,
			"settingStoreCookies": true,
			"url": "http://127.0.0.1:5002/nodes/register",
			"_type": "request"
		},
		{
			"_id": "req_da9999a934e34aa6b7ec8ac2b9bab34d",
			"authentication": {},
			"body": {},
			"created": 1698701659030,
			"description": "",
			"headers": [],
			"isPrivate": false,
			"metaSortKey": -1698701659030,
			"method": "GET",
			"modified": 1698713294238,
			"name": "resolve2",
			"parameters": [],
			"parentId": "fld_a13402fa5996453ba52c48b74f8d2c4f",
			"settingDisableRenderRequestBody": false,
			"settingEncodeUrl": true,
			"settingMaxTimelineDataSize": 1000,
			"settingRebuildPath": true,
			"settingSendCookies": true,
			"settingStoreCookies": true,
			"url": "http://127.0.0.1:5002/nodes/resolve",
			"_type": "request"
		}
	]
}